{"name":"HireNewEmployeeSaveDraftAndDeleteDraft","id":"org.icrc.hrspace.EC.HireAssignTerminate:HireNewEmployeeSaveDraftAndDeleteDraft","testCaseName":"org.icrc.hrspace.EC.HireAssignTerminate","testSteps":[{"number":1,"description":"When HR admin hires new employee: Bea Fe TEJANO, A851754, HRIS2022, 22/12/2022, Switzerland - Resident Staff HQ, New Hire, Mr., ZCtVSF, ZAjAOT, \u003cnull\u003e, ZCtVSF ZAjAOT, 22/06/1997, Testing, Uri, Switzerland, PeopleNet, Switzerland, Social Security Number, 7568604712491, Yes, Male, Switzerland, \u003cnull\u003e, \u003cnull\u003e, MARRIED, 09/09/2005, English, Test, Test, 5, \u003cnull\u003e, Switzerland, St. Gallen, Private, Personal, asdasd@asdsa.com, Yes, Cell, Philippines, 63, 09453364115, Yes, Mailing, Switzerland, No, TEST, Basel-Landschaft, TEST, TEST, TEST, 1234, Mr. Testing, PARTNER, Philippines, 09988727086, Yes, CH_RES_HQ, 22/12/2022, 22/12/2022, 40, 26/12/2021, Automation Testing, The Philippine National Red Cross, NOT APPLICABLE, No, Mobile staff - Maximum term contract, \u003cnull\u003e, 100% in pay, 1-1-1-1-1-0-0, Switzerland, CH Field Family, 22/12/2022, 22/12/2022, COMMENTS_IN_COMPENSATION_INFORMATION, 01/04/2022, Base Salary, 30000, \u003cnull\u003e, \u003cnull\u003e","duration":1339861,"startTime":"2022-12-22T08:03:32.968427200+08:00[Asia/Manila]","screenshots":[{"screenshot":"388141b6e2c2c571f6b8e9812100568c52a6f1ecfacabfb79963eebef5db22c4.png","timeStamp":1671668752830}],"result":"SUCCESS","precondition":false,"level":0,"children":[{"number":2,"description":"Given that I\u0027m logged in to HR space as \u0027Bea Fe TEJANO\u0027","duration":62503,"startTime":"2022-12-22T08:03:32.979321200+08:00[Asia/Manila]","screenshots":[{"screenshot":"76168387738e18b923b71992a49ff31215c687fa8ebefdbae11c288913deb0fa.png","timeStamp":1671667475483}],"result":"SUCCESS","precondition":false,"level":1,"children":[{"number":3,"description":"Given that I\u0027m logged in to HR space using \u0027A851754\u0027 account","duration":43164,"startTime":"2022-12-22T08:03:46.736095500+08:00[Asia/Manila]","screenshots":[{"screenshot":"c4fc17dd900931ae347d79700f0267cb591dd8aa07f352acf66cc05f07446cca.png","timeStamp":1671667426931},{"screenshot":"5286f211277bab15e57c8948ca4656f3f5d76cf0f9081467820a853560a48fc4.png","timeStamp":1671667441318},{"screenshot":"76168387738e18b923b71992a49ff31215c687fa8ebefdbae11c288913deb0fa.png","timeStamp":1671667464304},{"screenshot":"76168387738e18b923b71992a49ff31215c687fa8ebefdbae11c288913deb0fa.png","timeStamp":1671667469900}],"result":"SUCCESS","precondition":false,"level":2}]},{"number":4,"description":"When i search for an action using the header search bar: Add New Employee","duration":18805,"startTime":"2022-12-22T08:04:35.484888900+08:00[Asia/Manila]","screenshots":[{"screenshot":"76168387738e18b923b71992a49ff31215c687fa8ebefdbae11c288913deb0fa.png","timeStamp":1671667475497},{"screenshot":"1bd1dbe34755a80762da9bc01e12e9736b9590a3bb6be256ab159f24f95c2636.png","timeStamp":1671667494290}],"result":"SUCCESS","precondition":false,"level":1},{"number":5,"description":"When i populate hire date field: 22/12/2022","duration":17905,"startTime":"2022-12-22T08:04:54.293709500+08:00[Asia/Manila]","screenshots":[{"screenshot":"1bd1dbe34755a80762da9bc01e12e9736b9590a3bb6be256ab159f24f95c2636.png","timeStamp":1671667494308},{"screenshot":"3d54d2781341959e03461a011fe53388ac5f2f42dd9c650a4385b27132282678.png","timeStamp":1671667512199}],"result":"SUCCESS","precondition":false,"level":1},{"number":6,"description":"When i populate legal entity field: Switzerland - Resident Staff HQ","duration":25741,"startTime":"2022-12-22T08:05:12.201050500+08:00[Asia/Manila]","screenshots":[{"screenshot":"3d54d2781341959e03461a011fe53388ac5f2f42dd9c650a4385b27132282678.png","timeStamp":1671667512215},{"screenshot":"d77a8ae4286b61695d60493517a984a45935a08e3e9b1583f281924f112fa589.png","timeStamp":1671667519546},{"screenshot":"fc135b13e373bcd4c990a4a17a6157e0c0f39e78d8ab020c1ab72c62b1f141ed.png","timeStamp":1671667537942}],"result":"SUCCESS","precondition":false,"level":1},{"number":7,"description":"When i populate event reason field: New Hire","duration":11593,"startTime":"2022-12-22T08:05:37.944722+08:00[Asia/Manila]","screenshots":[{"screenshot":"fc135b13e373bcd4c990a4a17a6157e0c0f39e78d8ab020c1ab72c62b1f141ed.png","timeStamp":1671667537962},{"screenshot":"cc573685deab7d84d1a6dc847215241bfaa0d9db103ba635e58815af48121f1b.png","timeStamp":1671667544205},{"screenshot":"cc573685deab7d84d1a6dc847215241bfaa0d9db103ba635e58815af48121f1b.png","timeStamp":1671667549537}],"result":"SUCCESS","precondition":false,"level":1},{"number":8,"description":"When i populate title field: Mr.","duration":11467,"startTime":"2022-12-22T08:05:49.539590900+08:00[Asia/Manila]","screenshots":[{"screenshot":"cc573685deab7d84d1a6dc847215241bfaa0d9db103ba635e58815af48121f1b.png","timeStamp":1671667549555},{"screenshot":"a4d7e6a78bc69eaf285c4c46368567cffbfac14e055d1e380f3b192e102604a5.png","timeStamp":1671667555700},{"screenshot":"a4d7e6a78bc69eaf285c4c46368567cffbfac14e055d1e380f3b192e102604a5.png","timeStamp":1671667561006}],"result":"SUCCESS","precondition":false,"level":1},{"number":9,"description":"When i populate first name field: ZCtVSF","duration":11011,"startTime":"2022-12-22T08:06:01.008664+08:00[Asia/Manila]","screenshots":[{"screenshot":"a4d7e6a78bc69eaf285c4c46368567cffbfac14e055d1e380f3b192e102604a5.png","timeStamp":1671667561021},{"screenshot":"1acf34cc8275ce5ac36614c966b02466eb740ce158cf3659d31182887a1e271f.png","timeStamp":1671667572019}],"result":"SUCCESS","precondition":false,"level":1},{"number":10,"description":"When i populate last name field: ZAjAOT","duration":11007,"startTime":"2022-12-22T08:06:12.022885200+08:00[Asia/Manila]","screenshots":[{"screenshot":"1acf34cc8275ce5ac36614c966b02466eb740ce158cf3659d31182887a1e271f.png","timeStamp":1671667572038},{"screenshot":"91f3da21e4ad7fb8b975cac8182859435c54dcf1cdeb42e6348d24d485a1541a.png","timeStamp":1671667583029}],"result":"SUCCESS","precondition":false,"level":1},{"number":11,"description":"When i populate maiden name field: \u003cnull\u003e","duration":22,"startTime":"2022-12-22T08:06:23.031941700+08:00[Asia/Manila]","screenshots":[{"screenshot":"91f3da21e4ad7fb8b975cac8182859435c54dcf1cdeb42e6348d24d485a1541a.png","timeStamp":1671667583043},{"screenshot":"91f3da21e4ad7fb8b975cac8182859435c54dcf1cdeb42e6348d24d485a1541a.png","timeStamp":1671667583054}],"result":"SUCCESS","precondition":false,"level":1},{"number":12,"description":"When i populate date of birth field: 22/06/1997","duration":10881,"startTime":"2022-12-22T08:06:23.056802200+08:00[Asia/Manila]","screenshots":[{"screenshot":"91f3da21e4ad7fb8b975cac8182859435c54dcf1cdeb42e6348d24d485a1541a.png","timeStamp":1671667583070},{"screenshot":"22af3f95e1f0a8954e2aa52c7ea05ccd35aa2b3ea1f37b9cf79b4a02a9bccfdb.png","timeStamp":1671667593937}],"result":"SUCCESS","precondition":false,"level":1},{"number":13,"description":"When i populate town of birth field: Testing","duration":10905,"startTime":"2022-12-22T08:06:33.940319+08:00[Asia/Manila]","screenshots":[{"screenshot":"22af3f95e1f0a8954e2aa52c7ea05ccd35aa2b3ea1f37b9cf79b4a02a9bccfdb.png","timeStamp":1671667593953},{"screenshot":"8926fe555e6363e878d52dc8852510371b5c4f60f3048304d1472dcb7f3a3ddf.png","timeStamp":1671667604845}],"result":"SUCCESS","precondition":false,"level":1},{"number":14,"description":"When i populate county of birth field: Uri","duration":5343,"startTime":"2022-12-22T08:06:44.847397700+08:00[Asia/Manila]","screenshots":[{"screenshot":"8926fe555e6363e878d52dc8852510371b5c4f60f3048304d1472dcb7f3a3ddf.png","timeStamp":1671667604860},{"screenshot":"8926fe555e6363e878d52dc8852510371b5c4f60f3048304d1472dcb7f3a3ddf.png","timeStamp":1671667610190}],"result":"SUCCESS","precondition":false,"level":1},{"number":15,"description":"When i populate country of birth field: Switzerland","duration":11623,"startTime":"2022-12-22T08:06:50.192419100+08:00[Asia/Manila]","screenshots":[{"screenshot":"8926fe555e6363e878d52dc8852510371b5c4f60f3048304d1472dcb7f3a3ddf.png","timeStamp":1671667610209},{"screenshot":"39426440f4f75ea4641ae25beb8c78c5265641e938a852678d83675deda75eda.png","timeStamp":1671667616566},{"screenshot":"39426440f4f75ea4641ae25beb8c78c5265641e938a852678d83675deda75eda.png","timeStamp":1671667621816}],"result":"SUCCESS","precondition":false,"level":1},{"number":16,"description":"When i populate interface routing field: PeopleNet","duration":11421,"startTime":"2022-12-22T08:07:01.819217500+08:00[Asia/Manila]","screenshots":[{"screenshot":"39426440f4f75ea4641ae25beb8c78c5265641e938a852678d83675deda75eda.png","timeStamp":1671667621834},{"screenshot":"1a1e8faabdc476947d199b53de8a056cf983d4853239ca263e66b0a8493729eb.png","timeStamp":1671667627931},{"screenshot":"157d12f2e1c601a06cff5342c4794db3d32be53b13923a7dc0b76145fbf49257.png","timeStamp":1671667633240}],"result":"SUCCESS","precondition":false,"level":1},{"number":17,"description":"When i click add button in national ID: 7568604712491","duration":6160,"startTime":"2022-12-22T08:07:13.242622+08:00[Asia/Manila]","screenshots":[{"screenshot":"157d12f2e1c601a06cff5342c4794db3d32be53b13923a7dc0b76145fbf49257.png","timeStamp":1671667633253},{"screenshot":"5e68e785d42f65d1c80dd9b3bbdc771f8e3d2e2192c80160abf6742c319c0949.png","timeStamp":1671667634051},{"screenshot":"5e68e785d42f65d1c80dd9b3bbdc771f8e3d2e2192c80160abf6742c319c0949.png","timeStamp":1671667639403}],"result":"SUCCESS","precondition":false,"level":1},{"number":18,"description":"When i populate country in national ID: Switzerland","duration":9623,"startTime":"2022-12-22T08:07:19.404567900+08:00[Asia/Manila]","screenshots":[{"screenshot":"5e68e785d42f65d1c80dd9b3bbdc771f8e3d2e2192c80160abf6742c319c0949.png","timeStamp":1671667639418},{"screenshot":"f5b39a3e467b61ff95382956b7b8413585e075926357b0a1ec8ebf8f622979b1.png","timeStamp":1671667645737},{"screenshot":"f5b39a3e467b61ff95382956b7b8413585e075926357b0a1ec8ebf8f622979b1.png","timeStamp":1671667649028}],"result":"SUCCESS","precondition":false,"level":1},{"number":19,"description":"When i populate national ID card type in national ID: Social Security Number","duration":9709,"startTime":"2022-12-22T08:07:29.030246500+08:00[Asia/Manila]","screenshots":[{"screenshot":"f5b39a3e467b61ff95382956b7b8413585e075926357b0a1ec8ebf8f622979b1.png","timeStamp":1671667649041},{"screenshot":"ac4b322d3616b4327037fd9fd7cde408a930105c849ac548337259a8612d4507.png","timeStamp":1671667655431},{"screenshot":"540137a7a2aeef3ad6637e19ab20cc0298df76eaaedfaacde6eecd539c5e3a4e.png","timeStamp":1671667658739}],"result":"SUCCESS","precondition":false,"level":1},{"number":20,"description":"When i populate national ID: 7568604712491","duration":5969,"startTime":"2022-12-22T08:07:38.741531100+08:00[Asia/Manila]","screenshots":[{"screenshot":"540137a7a2aeef3ad6637e19ab20cc0298df76eaaedfaacde6eecd539c5e3a4e.png","timeStamp":1671667658751},{"screenshot":"300d38d303a15b3cebc8f364bed53217b39746ea13e3f5711ddb62e6b3969ede.png","timeStamp":1671667664710}],"result":"SUCCESS","precondition":false,"level":1},{"number":21,"description":"When i populate is primary in national ID: Yes","duration":5053,"startTime":"2022-12-22T08:07:44.712144600+08:00[Asia/Manila]","screenshots":[{"screenshot":"300d38d303a15b3cebc8f364bed53217b39746ea13e3f5711ddb62e6b3969ede.png","timeStamp":1671667664725},{"screenshot":"dbf2eb500f599fa55fec4b212c1e476b9bfaf1637b9d7c099700c46af6678adf.png","timeStamp":1671667665719},{"screenshot":"4ab007b4d8bca6a718827f0aea3693fa873b84573e4e5e94c9ccf52367da79df.png","timeStamp":1671667666419},{"screenshot":"4ab007b4d8bca6a718827f0aea3693fa873b84573e4e5e94c9ccf52367da79df.png","timeStamp":1671667669765}],"result":"SUCCESS","precondition":false,"level":1},{"number":22,"description":"When i click continue button","duration":4340,"startTime":"2022-12-22T08:07:49.767711800+08:00[Asia/Manila]","screenshots":[{"screenshot":"4ab007b4d8bca6a718827f0aea3693fa873b84573e4e5e94c9ccf52367da79df.png","timeStamp":1671667669779},{"screenshot":"60623d17867d0568dbbce4d7a2bca245511e770f1a5e4b8119726a23112d7c03.png","timeStamp":1671667670644},{"screenshot":"2309288417a010810a82a4044fd44b94ebe883c836865eea93045ebc1c1e836e.png","timeStamp":1671667674108}],"result":"SUCCESS","precondition":false,"level":1},{"number":23,"description":"When i click button in duplicate check: Ignore Matches","duration":44285,"startTime":"2022-12-22T08:07:54.118639+08:00[Asia/Manila]","screenshots":[{"screenshot":"2309288417a010810a82a4044fd44b94ebe883c836865eea93045ebc1c1e836e.png","timeStamp":1671667674142},{"screenshot":"70271d2b3ab9cb84c301d0cb7b50d4f7e0caddcbc9f0b2700aed5184a69e40d3.png","timeStamp":1671667718403}],"result":"SUCCESS","precondition":false,"level":1},{"number":24,"description":"When i populate gender: Male","duration":11715,"startTime":"2022-12-22T08:08:38.405809200+08:00[Asia/Manila]","screenshots":[{"screenshot":"70271d2b3ab9cb84c301d0cb7b50d4f7e0caddcbc9f0b2700aed5184a69e40d3.png","timeStamp":1671667718421},{"screenshot":"fad172c58694b0486c6a7342762e233509df59fe47bb723c669154b1fada6b5f.png","timeStamp":1671667724839},{"screenshot":"fad172c58694b0486c6a7342762e233509df59fe47bb723c669154b1fada6b5f.png","timeStamp":1671667730121}],"result":"SUCCESS","precondition":false,"level":1},{"number":25,"description":"When i populate nationality at birth: Switzerland","duration":11498,"startTime":"2022-12-22T08:08:50.123226100+08:00[Asia/Manila]","screenshots":[{"screenshot":"fad172c58694b0486c6a7342762e233509df59fe47bb723c669154b1fada6b5f.png","timeStamp":1671667730134},{"screenshot":"1c65136e8df070b05d344bb1c96cdfbac5f3ccbf4cf5f80d63f5f7a2dc6475c2.png","timeStamp":1671667736297},{"screenshot":"9c020a467da066a1d176ba5eef6c8bf3ea94413dba1be85f22f7212a3f895241.png","timeStamp":1671667741621}],"result":"SUCCESS","precondition":false,"level":1},{"number":26,"description":"When i populate current nationality: \u003cnull\u003e","duration":23,"startTime":"2022-12-22T08:09:01.624310100+08:00[Asia/Manila]","screenshots":[{"screenshot":"9c020a467da066a1d176ba5eef6c8bf3ea94413dba1be85f22f7212a3f895241.png","timeStamp":1671667741634},{"screenshot":"9c020a467da066a1d176ba5eef6c8bf3ea94413dba1be85f22f7212a3f895241.png","timeStamp":1671667741647}],"result":"SUCCESS","precondition":false,"level":1},{"number":27,"description":"When i populate other nationality: \u003cnull\u003e","duration":20,"startTime":"2022-12-22T08:09:01.648381200+08:00[Asia/Manila]","screenshots":[{"screenshot":"9c020a467da066a1d176ba5eef6c8bf3ea94413dba1be85f22f7212a3f895241.png","timeStamp":1671667741658},{"screenshot":"9c020a467da066a1d176ba5eef6c8bf3ea94413dba1be85f22f7212a3f895241.png","timeStamp":1671667741669}],"result":"SUCCESS","precondition":false,"level":1},{"number":28,"description":"When i populate marital status: MARRIED","duration":11664,"startTime":"2022-12-22T08:09:01.670649500+08:00[Asia/Manila]","screenshots":[{"screenshot":"9c020a467da066a1d176ba5eef6c8bf3ea94413dba1be85f22f7212a3f895241.png","timeStamp":1671667741838},{"screenshot":"466dfea9302d9917431114f04180c0df5684eb1b52d58c5f37b9165e3d0bb839.png","timeStamp":1671667747994},{"screenshot":"5046777c52ad6d491480ae7de9931a7e3ca4291ada72e408161ef9146c6f0723.png","timeStamp":1671667753334}],"result":"SUCCESS","precondition":false,"level":1},{"number":29,"description":"When i populate marital status since: 09/09/2005","duration":10929,"startTime":"2022-12-22T08:09:13.336891100+08:00[Asia/Manila]","screenshots":[{"screenshot":"5046777c52ad6d491480ae7de9931a7e3ca4291ada72e408161ef9146c6f0723.png","timeStamp":1671667753348},{"screenshot":"91ec68ef76fe768bec5ac38bb94f4ce87d5e551226ab90be1bcf6a5603cdded1.png","timeStamp":1671667764266}],"result":"SUCCESS","precondition":false,"level":1},{"number":30,"description":"When i populate mailing preferred language: English","duration":11543,"startTime":"2022-12-22T08:09:24.268367800+08:00[Asia/Manila]","screenshots":[{"screenshot":"91ec68ef76fe768bec5ac38bb94f4ce87d5e551226ab90be1bcf6a5603cdded1.png","timeStamp":1671667764281},{"screenshot":"704007ee9d6c1b4688de59184f51d5cb2d9b70be131f6568cf380b8dee318566.png","timeStamp":1671667770469},{"screenshot":"791dd0cbf51256e5c47558902271c32f79f960cb22f5cf9516caf7f4bc2a50bf.png","timeStamp":1671667775811}],"result":"SUCCESS","precondition":false,"level":1},{"number":31,"description":"When i populate religion: Test","duration":10878,"startTime":"2022-12-22T08:09:35.813746500+08:00[Asia/Manila]","screenshots":[{"screenshot":"791dd0cbf51256e5c47558902271c32f79f960cb22f5cf9516caf7f4bc2a50bf.png","timeStamp":1671667775824},{"screenshot":"2298966a58fb39be470fe6094683bbf2c90930ccb9460d52a84f7806c019117a.png","timeStamp":1671667786691}],"result":"SUCCESS","precondition":false,"level":1},{"number":32,"description":"When i populate ethnic group: Test","duration":10928,"startTime":"2022-12-22T08:09:46.693957600+08:00[Asia/Manila]","screenshots":[{"screenshot":"2298966a58fb39be470fe6094683bbf2c90930ccb9460d52a84f7806c019117a.png","timeStamp":1671667786707},{"screenshot":"d6b0f4bca34911929797cf608a28fac073b6994dd0edb0548477b6a6a7d1603f.png","timeStamp":1671667797622}],"result":"SUCCESS","precondition":false,"level":1},{"number":33,"description":"When i populate number of children: 5","duration":10874,"startTime":"2022-12-22T08:09:57.623642700+08:00[Asia/Manila]","screenshots":[{"screenshot":"d6b0f4bca34911929797cf608a28fac073b6994dd0edb0548477b6a6a7d1603f.png","timeStamp":1671667797634},{"screenshot":"f26038dbf9d3d56d301f61a01681ce1100e01c238cc9af4c70c47ca575140580.png","timeStamp":1671667808497}],"result":"SUCCESS","precondition":false,"level":1},{"number":34,"description":"When i populate rapid deployment: \u003cnull\u003e","duration":22,"startTime":"2022-12-22T08:10:08.499769200+08:00[Asia/Manila]","screenshots":[{"screenshot":"f26038dbf9d3d56d301f61a01681ce1100e01c238cc9af4c70c47ca575140580.png","timeStamp":1671667808512},{"screenshot":"f26038dbf9d3d56d301f61a01681ce1100e01c238cc9af4c70c47ca575140580.png","timeStamp":1671667808522}],"result":"SUCCESS","precondition":false,"level":1},{"number":35,"description":"When i populate country region: Switzerland","duration":275,"startTime":"2022-12-22T08:10:08.523198700+08:00[Asia/Manila]","screenshots":[{"screenshot":"f26038dbf9d3d56d301f61a01681ce1100e01c238cc9af4c70c47ca575140580.png","timeStamp":1671667808535},{"screenshot":"2316274c4b6753b317f5a64c9f1b0c842fdf0bc69ea7fced019fcfbce318e2df.png","timeStamp":1671667808799}],"result":"SUCCESS","precondition":false,"level":1},{"number":36,"description":"When i populate canton of origin: St. Gallen","duration":11522,"startTime":"2022-12-22T08:10:08.800922500+08:00[Asia/Manila]","screenshots":[{"screenshot":"2316274c4b6753b317f5a64c9f1b0c842fdf0bc69ea7fced019fcfbce318e2df.png","timeStamp":1671667808811},{"screenshot":"d16ebe3342711df62b7e1a244bfae7581d994420d6e0087642fe1cb7085343dd.png","timeStamp":1671667815056},{"screenshot":"d16ebe3342711df62b7e1a244bfae7581d994420d6e0087642fe1cb7085343dd.png","timeStamp":1671667820323}],"result":"SUCCESS","precondition":false,"level":1},{"number":37,"description":"When i populate military rank: Private","duration":10918,"startTime":"2022-12-22T08:10:20.325495800+08:00[Asia/Manila]","screenshots":[{"screenshot":"d16ebe3342711df62b7e1a244bfae7581d994420d6e0087642fe1cb7085343dd.png","timeStamp":1671667820335},{"screenshot":"d3e790e81d07d05f64994032d2ee2af8e14763d135e398c5669e905ab7a70521.png","timeStamp":1671667831244}],"result":"SUCCESS","precondition":false,"level":1},{"number":38,"description":"When i click add button in email information","duration":6035,"startTime":"2022-12-22T08:10:31.246177+08:00[Asia/Manila]","screenshots":[{"screenshot":"d3e790e81d07d05f64994032d2ee2af8e14763d135e398c5669e905ab7a70521.png","timeStamp":1671667831257},{"screenshot":"7628a0211532af62986be6292ff3ebb23d90ab817cf28cf274d211449461c915.png","timeStamp":1671667832011},{"screenshot":"7628a0211532af62986be6292ff3ebb23d90ab817cf28cf274d211449461c915.png","timeStamp":1671667837282}],"result":"SUCCESS","precondition":false,"level":1},{"number":39,"description":"When i populate email type: Personal","duration":9710,"startTime":"2022-12-22T08:10:37.283129+08:00[Asia/Manila]","screenshots":[{"screenshot":"7628a0211532af62986be6292ff3ebb23d90ab817cf28cf274d211449461c915.png","timeStamp":1671667837293},{"screenshot":"2dde9ff70dce42ea8079893e19c4b5e04e1d0ce73c5e2c0df95897134c16552e.png","timeStamp":1671667843654},{"screenshot":"2dde9ff70dce42ea8079893e19c4b5e04e1d0ce73c5e2c0df95897134c16552e.png","timeStamp":1671667846993}],"result":"SUCCESS","precondition":false,"level":1},{"number":40,"description":"When i populate email address: asdasd@asdsa.com","duration":5873,"startTime":"2022-12-22T08:10:46.994878400+08:00[Asia/Manila]","screenshots":[{"screenshot":"2dde9ff70dce42ea8079893e19c4b5e04e1d0ce73c5e2c0df95897134c16552e.png","timeStamp":1671667847004},{"screenshot":"59145150cf7d45da5c38c09a2575c1bb9a4d77b4293e26b7047e7171b5e6a705.png","timeStamp":1671667852868}],"result":"SUCCESS","precondition":false,"level":1},{"number":41,"description":"When i populate is primary in email information: Yes","duration":5249,"startTime":"2022-12-22T08:10:52.869115900+08:00[Asia/Manila]","screenshots":[{"screenshot":"59145150cf7d45da5c38c09a2575c1bb9a4d77b4293e26b7047e7171b5e6a705.png","timeStamp":1671667852878},{"screenshot":"1babec0ae4673447aed613ee26ed03988328a62ed2cbb747ce562a3bc3307c57.png","timeStamp":1671667854145},{"screenshot":"946893ddaf2859e6b26255c4222e54a906e35843343bdd72902f617d38e28160.png","timeStamp":1671667854781},{"screenshot":"946893ddaf2859e6b26255c4222e54a906e35843343bdd72902f617d38e28160.png","timeStamp":1671667858118}],"result":"SUCCESS","precondition":false,"level":1},{"number":42,"description":"When i click add button in phone information","duration":6097,"startTime":"2022-12-22T08:10:58.120992+08:00[Asia/Manila]","screenshots":[{"screenshot":"946893ddaf2859e6b26255c4222e54a906e35843343bdd72902f617d38e28160.png","timeStamp":1671667858131},{"screenshot":"268b7a0e9b662281b07b4729e3b80c7b49eb009b064d9b9f83a29f6997e83fd3.png","timeStamp":1671667858906},{"screenshot":"268b7a0e9b662281b07b4729e3b80c7b49eb009b064d9b9f83a29f6997e83fd3.png","timeStamp":1671667864218}],"result":"SUCCESS","precondition":false,"level":1},{"number":43,"description":"When i populate phone type: Cell","duration":8118,"startTime":"2022-12-22T08:11:04.219668700+08:00[Asia/Manila]","screenshots":[{"screenshot":"268b7a0e9b662281b07b4729e3b80c7b49eb009b064d9b9f83a29f6997e83fd3.png","timeStamp":1671667864230},{"screenshot":"63c2fdb8a8a4043749a58ee347045a4e5bdb0326ed7058aa38bb9975a14c420b.png","timeStamp":1671667870529},{"screenshot":"3a93b0898596d5516715e3529bdfcb07242176c99808c249463e9d9f3657fa3e.png","timeStamp":1671667872338}],"result":"SUCCESS","precondition":false,"level":1},{"number":44,"description":"When i populate country in phone information: Philippines","duration":9655,"startTime":"2022-12-22T08:11:12.340266900+08:00[Asia/Manila]","screenshots":[{"screenshot":"3a93b0898596d5516715e3529bdfcb07242176c99808c249463e9d9f3657fa3e.png","timeStamp":1671667872351},{"screenshot":"557b3f32332bdd44e5c6804ae2d2000c21ac107658676cbaa48af8b601b25355.png","timeStamp":1671667878676},{"screenshot":"af81a7d4fb7d946bfa57260a1d24615eed6ce95c18973025e67bd34b34e6e4f9.png","timeStamp":1671667881995}],"result":"SUCCESS","precondition":false,"level":1},{"number":45,"description":"When i populate country code: 63","duration":9733,"startTime":"2022-12-22T08:11:21.997432+08:00[Asia/Manila]","screenshots":[{"screenshot":"af81a7d4fb7d946bfa57260a1d24615eed6ce95c18973025e67bd34b34e6e4f9.png","timeStamp":1671667882011},{"screenshot":"43842b0961a206cb651b67969f295edf255c91c5ae61ac41740ab12470b78f44.png","timeStamp":1671667888368},{"screenshot":"43842b0961a206cb651b67969f295edf255c91c5ae61ac41740ab12470b78f44.png","timeStamp":1671667891730}],"result":"SUCCESS","precondition":false,"level":1},{"number":46,"description":"When i populate phone number in phone information: 09453364115","duration":5900,"startTime":"2022-12-22T08:11:31.732680800+08:00[Asia/Manila]","screenshots":[{"screenshot":"43842b0961a206cb651b67969f295edf255c91c5ae61ac41740ab12470b78f44.png","timeStamp":1671667891741},{"screenshot":"03161f1ca865ba9a9508f04541abf0c8aba71b701e3e040889b4d54fcee62c9e.png","timeStamp":1671667897633}],"result":"SUCCESS","precondition":false,"level":1},{"number":47,"description":"When i populate is primary in phone information: Yes","duration":5362,"startTime":"2022-12-22T08:11:37.634136900+08:00[Asia/Manila]","screenshots":[{"screenshot":"03161f1ca865ba9a9508f04541abf0c8aba71b701e3e040889b4d54fcee62c9e.png","timeStamp":1671667897646},{"screenshot":"2dd10bf2bc95de1668d313a8c805544848089f7f2d24aac2c6dcda4f1c4bc60d.png","timeStamp":1671667898986},{"screenshot":"111faf782a93f4d47ef02227fac2dcadb998bd263d8d052c892369d1cd002c4d.png","timeStamp":1671667899634},{"screenshot":"111faf782a93f4d47ef02227fac2dcadb998bd263d8d052c892369d1cd002c4d.png","timeStamp":1671667902996}],"result":"SUCCESS","precondition":false,"level":1},{"number":48,"description":"When i populate address type: Mailing","duration":274,"startTime":"2022-12-22T08:11:42.998365500+08:00[Asia/Manila]","screenshots":[{"screenshot":"111faf782a93f4d47ef02227fac2dcadb998bd263d8d052c892369d1cd002c4d.png","timeStamp":1671667903010},{"screenshot":"111faf782a93f4d47ef02227fac2dcadb998bd263d8d052c892369d1cd002c4d.png","timeStamp":1671667903273}],"result":"SUCCESS","precondition":false,"level":1},{"number":49,"description":"When i populate country: Switzerland","duration":282,"startTime":"2022-12-22T08:11:43.275186700+08:00[Asia/Manila]","screenshots":[{"screenshot":"111faf782a93f4d47ef02227fac2dcadb998bd263d8d052c892369d1cd002c4d.png","timeStamp":1671667903286},{"screenshot":"d54622168f7427d365a8fbfdcf340c3f437f945f232562d5f2edbb73027c16b7.png","timeStamp":1671667903557}],"result":"SUCCESS","precondition":false,"level":1},{"number":50,"description":"When i populate for employees under swiss contract: No","duration":11528,"startTime":"2022-12-22T08:11:43.559835+08:00[Asia/Manila]","screenshots":[{"screenshot":"d54622168f7427d365a8fbfdcf340c3f437f945f232562d5f2edbb73027c16b7.png","timeStamp":1671667903573},{"screenshot":"4b71675e35f48368a2e59f5947de2dc2658f77b2fea60261a14885404072a8ae.png","timeStamp":1671667909872},{"screenshot":"f64fa6fb519f24ad5923b06e818d9ac3c53762ad5123cbe4a92b36181562ade4.png","timeStamp":1671667915088}],"result":"SUCCESS","precondition":false,"level":1},{"number":51,"description":"When i populate town: TEST","duration":5790,"startTime":"2022-12-22T08:11:55.090170400+08:00[Asia/Manila]","screenshots":[{"screenshot":"f64fa6fb519f24ad5923b06e818d9ac3c53762ad5123cbe4a92b36181562ade4.png","timeStamp":1671667915104},{"screenshot":"fb8065d42fc5a8ed5f88fd479725cd9e98367f07781d47235cf9fac23ef1a79f.png","timeStamp":1671667920880}],"result":"SUCCESS","precondition":false,"level":1},{"number":52,"description":"When i populate county: Basel-Landschaft","duration":7441,"startTime":"2022-12-22T08:12:00.882181100+08:00[Asia/Manila]","screenshots":[{"screenshot":"fb8065d42fc5a8ed5f88fd479725cd9e98367f07781d47235cf9fac23ef1a79f.png","timeStamp":1671667920896},{"screenshot":"3d614d8533f447a8691341f3817a7fc1cef631dff6ee87064c1e0d05b97efeba.png","timeStamp":1671667922974},{"screenshot":"3d614d8533f447a8691341f3817a7fc1cef631dff6ee87064c1e0d05b97efeba.png","timeStamp":1671667928323}],"result":"SUCCESS","precondition":false,"level":1},{"number":53,"description":"When i populate address line 1: TEST","duration":5868,"startTime":"2022-12-22T08:12:08.324656+08:00[Asia/Manila]","screenshots":[{"screenshot":"3d614d8533f447a8691341f3817a7fc1cef631dff6ee87064c1e0d05b97efeba.png","timeStamp":1671667928334},{"screenshot":"5772d5f58cf44e994d906103043a312753080a7de089d7f6264ce61e404b34ea.png","timeStamp":1671667934193}],"result":"SUCCESS","precondition":false,"level":1},{"number":54,"description":"When i populate address line 2: TEST","duration":10914,"startTime":"2022-12-22T08:12:14.194504100+08:00[Asia/Manila]","screenshots":[{"screenshot":"5772d5f58cf44e994d906103043a312753080a7de089d7f6264ce61e404b34ea.png","timeStamp":1671667934206},{"screenshot":"d842820c8cbc36009f800b74edd3140d30afee13887ca78deb341666d902ba3d.png","timeStamp":1671667945108}],"result":"SUCCESS","precondition":false,"level":1},{"number":55,"description":"When i populate address line 3: TEST","duration":10898,"startTime":"2022-12-22T08:12:25.110562100+08:00[Asia/Manila]","screenshots":[{"screenshot":"d842820c8cbc36009f800b74edd3140d30afee13887ca78deb341666d902ba3d.png","timeStamp":1671667945128},{"screenshot":"84a015b8bb9d6291d7b9c29c3ebc9da29323c82deff796be430f8bc753853dd3.png","timeStamp":1671667956009}],"result":"SUCCESS","precondition":false,"level":1},{"number":56,"description":"When i populate postal code: 1234","duration":5849,"startTime":"2022-12-22T08:12:36.010764800+08:00[Asia/Manila]","screenshots":[{"screenshot":"84a015b8bb9d6291d7b9c29c3ebc9da29323c82deff796be430f8bc753853dd3.png","timeStamp":1671667956020},{"screenshot":"a35322f801fa124b18cd59c65675338175fa4635fc58e5efe91cbed55d168e4f.png","timeStamp":1671667961860}],"result":"SUCCESS","precondition":false,"level":1},{"number":57,"description":"When i click add emergency contact information button","duration":6253,"startTime":"2022-12-22T08:14:21.211233+08:00[Asia/Manila]","screenshots":[{"screenshot":"a35322f801fa124b18cd59c65675338175fa4635fc58e5efe91cbed55d168e4f.png","timeStamp":1671668061428},{"screenshot":"b4a3d5668ca79c0b4543b019ffc48cca2e0549618fed908a5ce34de3b5a622d1.png","timeStamp":1671668062188},{"screenshot":"b6c9eaca9158df9ff2c63e9c4ef2900e4067f9e614b544d7b30a5fbf97135ec3.png","timeStamp":1671668067464}],"result":"SUCCESS","precondition":false,"level":1},{"number":58,"description":"When i populate title and contract name: Mr. Testing","duration":10827,"startTime":"2022-12-22T08:14:27.466674100+08:00[Asia/Manila]","screenshots":[{"screenshot":"b6c9eaca9158df9ff2c63e9c4ef2900e4067f9e614b544d7b30a5fbf97135ec3.png","timeStamp":1671668067475},{"screenshot":"2acf5f71bdb9c8dbf16e43ccc3eb7bfbd95d36744ed8d0fae5669c37e077d7a7.png","timeStamp":1671668078294}],"result":"SUCCESS","precondition":false,"level":1},{"number":59,"description":"When i populate dependent type: PARTNER","duration":11452,"startTime":"2022-12-22T08:14:38.295544200+08:00[Asia/Manila]","screenshots":[{"screenshot":"2acf5f71bdb9c8dbf16e43ccc3eb7bfbd95d36744ed8d0fae5669c37e077d7a7.png","timeStamp":1671668078307},{"screenshot":"9aac782b0726b7bf5813325fab226e2d288109271318cebf59459d5e97fb5fc3.png","timeStamp":1671668084451},{"screenshot":"9aac782b0726b7bf5813325fab226e2d288109271318cebf59459d5e97fb5fc3.png","timeStamp":1671668089747}],"result":"SUCCESS","precondition":false,"level":1},{"number":60,"description":"When i populate country in emergency contact information: Philippines","duration":11515,"startTime":"2022-12-22T08:14:49.748575300+08:00[Asia/Manila]","screenshots":[{"screenshot":"9aac782b0726b7bf5813325fab226e2d288109271318cebf59459d5e97fb5fc3.png","timeStamp":1671668089757},{"screenshot":"78e4f30a30df882092a01d17f1d0f76a4afec30f31597565662569d9a9a04bd6.png","timeStamp":1671668095892},{"screenshot":"78e4f30a30df882092a01d17f1d0f76a4afec30f31597565662569d9a9a04bd6.png","timeStamp":1671668101263}],"result":"SUCCESS","precondition":false,"level":1},{"number":61,"description":"When i populate phone number: 09453364115","duration":10864,"startTime":"2022-12-22T08:15:01.265949+08:00[Asia/Manila]","screenshots":[{"screenshot":"78e4f30a30df882092a01d17f1d0f76a4afec30f31597565662569d9a9a04bd6.png","timeStamp":1671668101274},{"screenshot":"23c2f620d12d2c4b8c52a50c66c8eb0056dbbdf09757ade3d390f41f97ea6f76.png","timeStamp":1671668112130}],"result":"SUCCESS","precondition":false,"level":1},{"number":62,"description":"When i populate yes will be contacted first: Yes","duration":11553,"startTime":"2022-12-22T08:15:12.131444600+08:00[Asia/Manila]","screenshots":[{"screenshot":"23c2f620d12d2c4b8c52a50c66c8eb0056dbbdf09757ade3d390f41f97ea6f76.png","timeStamp":1671668112141},{"screenshot":"fb7203af649eb9813eb209875ac03e1b8d5f7a68b68f542e8fb92a3711eae962.png","timeStamp":1671668118338},{"screenshot":"fb7203af649eb9813eb209875ac03e1b8d5f7a68b68f542e8fb92a3711eae962.png","timeStamp":1671668123684}],"result":"SUCCESS","precondition":false,"level":1},{"number":63,"description":"When i click continue button in address portlet","duration":5308,"startTime":"2022-12-22T08:15:30.584388600+08:00[Asia/Manila]","screenshots":[{"screenshot":"fb7203af649eb9813eb209875ac03e1b8d5f7a68b68f542e8fb92a3711eae962.png","timeStamp":1671668130819},{"screenshot":"3f59929ad2dee9a1fd0a75eed7667f29fd2abd7256a4fb67d727e70e5d3922e3.png","timeStamp":1671668131656},{"screenshot":"9f65d7fbe01d6e664a7ca472a780c455ed4dd390199b6e87f3248edf6576bb3d.png","timeStamp":1671668135892}],"result":"SUCCESS","precondition":false,"level":1},{"number":64,"description":"When i populate position: CH_RES_HQ","duration":11684,"startTime":"2022-12-22T08:16:34.659909200+08:00[Asia/Manila]","screenshots":[{"screenshot":"5190ae023549605d033939561f23f16ff2699ef8177743bdeb29b28e70c5009c.png","timeStamp":1671668194867},{"screenshot":"6e74f33a42daf0d5c5b3316deb1650595bbb454094cf611a12e2b7926804f926.png","timeStamp":1671668201030},{"screenshot":"e2dbea511ea89e2e00ed980f16863f66c459cd78009364f1da91d5d1f6e9c597.png","timeStamp":1671668206344}],"result":"SUCCESS","precondition":false,"level":1},{"number":65,"description":"When i populate comments: Automation Testing","duration":5668,"startTime":"2022-12-22T08:16:46.345612300+08:00[Asia/Manila]","screenshots":[{"screenshot":"e2dbea511ea89e2e00ed980f16863f66c459cd78009364f1da91d5d1f6e9c597.png","timeStamp":1671668206355},{"screenshot":"62af2e20d58b29c2bd09db93d13d9a3a8b77288b2e17707b76a6d75c8ce4731d.png","timeStamp":1671668212013}],"result":"SUCCESS","precondition":false,"level":1},{"number":66,"description":"When i populate assignment estimated end date: 22/12/2022","duration":5860,"startTime":"2022-12-22T08:16:52.014442800+08:00[Asia/Manila]","screenshots":[{"screenshot":"62af2e20d58b29c2bd09db93d13d9a3a8b77288b2e17707b76a6d75c8ce4731d.png","timeStamp":1671668212025},{"screenshot":"a541d22f165ae22747a5842b04cfdccebfe2020cba434dd3cf55afb652af6d83.png","timeStamp":1671668217875}],"result":"SUCCESS","precondition":false,"level":1},{"number":67,"description":"When i populate contract estimated end date: 22/12/2022","duration":5896,"startTime":"2022-12-22T08:16:57.876144300+08:00[Asia/Manila]","screenshots":[{"screenshot":"a541d22f165ae22747a5842b04cfdccebfe2020cba434dd3cf55afb652af6d83.png","timeStamp":1671668217887},{"screenshot":"2ff0990eb03550a7c5ec17714f01b73433f4750d44c2111e7f37fc2b7f55cac5.png","timeStamp":1671668223772}],"result":"SUCCESS","precondition":false,"level":1},{"number":68,"description":"When i populate effective weekly hours: 40","duration":5481,"startTime":"2022-12-22T08:17:03.773248100+08:00[Asia/Manila]","screenshots":[{"screenshot":"2ff0990eb03550a7c5ec17714f01b73433f4750d44c2111e7f37fc2b7f55cac5.png","timeStamp":1671668223784},{"screenshot":"2ff0990eb03550a7c5ec17714f01b73433f4750d44c2111e7f37fc2b7f55cac5.png","timeStamp":1671668229254}],"result":"SUCCESS","precondition":false,"level":1},{"number":69,"description":"When i populate probation period end date: 26/12/2021","duration":11003,"startTime":"2022-12-22T08:17:09.255570+08:00[Asia/Manila]","screenshots":[{"screenshot":"2ff0990eb03550a7c5ec17714f01b73433f4750d44c2111e7f37fc2b7f55cac5.png","timeStamp":1671668229265},{"screenshot":"76f9741aac044247086f49cff93dba8f5077bc4b9f8cf51e9aeb89c4fc427457.png","timeStamp":1671668240258}],"result":"SUCCESS","precondition":false,"level":1},{"number":70,"description":"When i populate national society code: The Philippine National Red Cross","duration":11672,"startTime":"2022-12-22T08:17:20.259775600+08:00[Asia/Manila]","screenshots":[{"screenshot":"76f9741aac044247086f49cff93dba8f5077bc4b9f8cf51e9aeb89c4fc427457.png","timeStamp":1671668240271},{"screenshot":"f835cb62145bdba3f44e82ad76870771cf69c4065ad040befacbaf48027f8275.png","timeStamp":1671668246605},{"screenshot":"f835cb62145bdba3f44e82ad76870771cf69c4065ad040befacbaf48027f8275.png","timeStamp":1671668251932}],"result":"SUCCESS","precondition":false,"level":1},{"number":71,"description":"When i populate position person fit: NOT APPLICABLE","duration":11536,"startTime":"2022-12-22T08:17:31.933719200+08:00[Asia/Manila]","screenshots":[{"screenshot":"f835cb62145bdba3f44e82ad76870771cf69c4065ad040befacbaf48027f8275.png","timeStamp":1671668251946},{"screenshot":"9a473e846dbce8fbf1556df643971957bf868f9203bde74293a2f2959d0e3c50.png","timeStamp":1671668258210},{"screenshot":"9a473e846dbce8fbf1556df643971957bf868f9203bde74293a2f2959d0e3c50.png","timeStamp":1671668263470}],"result":"SUCCESS","precondition":false,"level":1},{"number":72,"description":"When i populate confirmed: No","duration":11501,"startTime":"2022-12-22T08:17:43.472287600+08:00[Asia/Manila]","screenshots":[{"screenshot":"9a473e846dbce8fbf1556df643971957bf868f9203bde74293a2f2959d0e3c50.png","timeStamp":1671668263482},{"screenshot":"cede7af8bfda1709cdd543cf02c5140285c353a5a90fe2d5122a73a26b454f77.png","timeStamp":1671668269644},{"screenshot":"cede7af8bfda1709cdd543cf02c5140285c353a5a90fe2d5122a73a26b454f77.png","timeStamp":1671668274973}],"result":"SUCCESS","precondition":false,"level":1},{"number":73,"description":"When i populate contract type: Mobile staff - Maximum term contract","duration":25746,"startTime":"2022-12-22T08:17:54.974113700+08:00[Asia/Manila]","screenshots":[{"screenshot":"cede7af8bfda1709cdd543cf02c5140285c353a5a90fe2d5122a73a26b454f77.png","timeStamp":1671668274986},{"screenshot":"917ed2be8fb38aa85da9fe9250fec8712687fff45fd39d62bda494b2c841a77d.png","timeStamp":1671668282324},{"screenshot":"cd3ed23cc18924ac669f6fc3dd63b5df4b7ad25c24550009068cdaf5f143d0d0.png","timeStamp":1671668300721}],"result":"SUCCESS","precondition":false,"level":1},{"number":74,"description":"Then a confirmation message is displayed after populating contract type","duration":11503,"startTime":"2022-12-22T08:18:20.722002900+08:00[Asia/Manila]","screenshots":[{"screenshot":"cd3ed23cc18924ac669f6fc3dd63b5df4b7ad25c24550009068cdaf5f143d0d0.png","timeStamp":1671668300731},{"screenshot":"f6974681b3187dcb5ec06c1352bd57ad35b057a46b2720b5b44c958e57641449.png","timeStamp":1671668312225}],"result":"SUCCESS","precondition":false,"level":1,"children":[{"number":75,"description":"When i click ok button","duration":6247,"startTime":"2022-12-22T08:18:25.966031400+08:00[Asia/Manila]","screenshots":[{"screenshot":"cd3ed23cc18924ac669f6fc3dd63b5df4b7ad25c24550009068cdaf5f143d0d0.png","timeStamp":1671668306139},{"screenshot":"57d148b9e9ba736026b5c381e89449b57a7070830ee7630f1efe31d629c39a85.png","timeStamp":1671668306968},{"screenshot":"f6974681b3187dcb5ec06c1352bd57ad35b057a46b2720b5b44c958e57641449.png","timeStamp":1671668312213}],"result":"SUCCESS","precondition":false,"level":2}]},{"number":76,"description":"When i populate UCC assignment: ADMIN","duration":11710,"startTime":"2022-12-22T08:18:50.821190600+08:00[Asia/Manila]","screenshots":[{"screenshot":"f6974681b3187dcb5ec06c1352bd57ad35b057a46b2720b5b44c958e57641449.png","timeStamp":1671668331074},{"screenshot":"66974ed1a09e1f2b0dc02782dae870d553b9ff8b5b870f43abccd03881f72d7a.png","timeStamp":1671668337248},{"screenshot":"66974ed1a09e1f2b0dc02782dae870d553b9ff8b5b870f43abccd03881f72d7a.png","timeStamp":1671668342531}],"result":"SUCCESS","precondition":false,"level":1},{"number":77,"description":"When i populate assignment mailing language: English","duration":7332,"startTime":"2022-12-22T08:19:44.414882300+08:00[Asia/Manila]","screenshots":[{"screenshot":"66974ed1a09e1f2b0dc02782dae870d553b9ff8b5b870f43abccd03881f72d7a.png","timeStamp":1671668384633},{"screenshot":"934fe09fe680495f08958da4d2bb37f4456ffe189dc907b9d2d65c00f3c2f52e.png","timeStamp":1671668385319},{"screenshot":"184b85be7694df289010ee4995c6643cc4c34ef96f6332d819c9b6e779b0215c.png","timeStamp":1671668386412},{"screenshot":"184b85be7694df289010ee4995c6643cc4c34ef96f6332d819c9b6e779b0215c.png","timeStamp":1671668391747}],"result":"SUCCESS","precondition":false,"level":1},{"number":78,"description":"When i populate hardship incentive option: 100% in pay","duration":11487,"startTime":"2022-12-22T08:19:51.748611200+08:00[Asia/Manila]","screenshots":[{"screenshot":"184b85be7694df289010ee4995c6643cc4c34ef96f6332d819c9b6e779b0215c.png","timeStamp":1671668391764},{"screenshot":"4cbb370fc557e5fbed8233b8f12cadeafcfd135d0e9a41a5d15959cdc274deaa.png","timeStamp":1671668397989},{"screenshot":"4cbb370fc557e5fbed8233b8f12cadeafcfd135d0e9a41a5d15959cdc274deaa.png","timeStamp":1671668403236}],"result":"SUCCESS","precondition":false,"level":1},{"number":79,"description":"When I populate Work Schedule","duration":25713,"startTime":"2022-12-22T08:20:03.238072500+08:00[Asia/Manila]","screenshots":[{"screenshot":"4cbb370fc557e5fbed8233b8f12cadeafcfd135d0e9a41a5d15959cdc274deaa.png","timeStamp":1671668403249},{"screenshot":"a00dbb83127ae314d24ecec2ac12b57aa85f55b816dc1be7b75a1a0e714fcc9d.png","timeStamp":1671668410605},{"screenshot":"a00dbb83127ae314d24ecec2ac12b57aa85f55b816dc1be7b75a1a0e714fcc9d.png","timeStamp":1671668428951}],"result":"SUCCESS","precondition":false,"level":1},{"number":80,"description":"When i populate holiday calendar: Switzerland","duration":25593,"startTime":"2022-12-22T08:20:28.952587600+08:00[Asia/Manila]","screenshots":[{"screenshot":"a00dbb83127ae314d24ecec2ac12b57aa85f55b816dc1be7b75a1a0e714fcc9d.png","timeStamp":1671668428962},{"screenshot":"37732de89e23284a0c4574185d74fb682ca44aa854b6c5b49f3c78e1b11f6c30.png","timeStamp":1671668436228},{"screenshot":"37732de89e23284a0c4574185d74fb682ca44aa854b6c5b49f3c78e1b11f6c30.png","timeStamp":1671668454545}],"result":"SUCCESS","precondition":false,"level":1},{"number":81,"description":"When i populate time profile: CH Field Family","duration":25734,"startTime":"2022-12-22T08:20:54.547691+08:00[Asia/Manila]","screenshots":[{"screenshot":"37732de89e23284a0c4574185d74fb682ca44aa854b6c5b49f3c78e1b11f6c30.png","timeStamp":1671668454559},{"screenshot":"ff7794243ef013852353f26e8e11a5f0c84134b0dc5b40e7aca71d29c311c764.png","timeStamp":1671668461858},{"screenshot":"c0182a3d96856d42c0778ea3103f46b531c6efafec54848c557ef96f836ee977.png","timeStamp":1671668480282}],"result":"SUCCESS","precondition":false,"level":1},{"number":82,"description":"When i populate hire date under employment details: 22/12/2022","duration":5466,"startTime":"2022-12-22T08:21:20.284452+08:00[Asia/Manila]","screenshots":[{"screenshot":"c0182a3d96856d42c0778ea3103f46b531c6efafec54848c557ef96f836ee977.png","timeStamp":1671668480296},{"screenshot":"dbb11210623cb5178d58cd50c352dce1f2097bb674cc20f957abb1bd52684506.png","timeStamp":1671668485751}],"result":"SUCCESS","precondition":false,"level":1},{"number":83,"description":"When i populate start date of 1st ICRC contract: 22/12/2022","duration":5473,"startTime":"2022-12-22T08:21:25.752076+08:00[Asia/Manila]","screenshots":[{"screenshot":"dbb11210623cb5178d58cd50c352dce1f2097bb674cc20f957abb1bd52684506.png","timeStamp":1671668485763},{"screenshot":"dbb11210623cb5178d58cd50c352dce1f2097bb674cc20f957abb1bd52684506.png","timeStamp":1671668491225}],"result":"SUCCESS","precondition":false,"level":1},{"number":84,"description":"When i populate eosi start date: 22/12/2022","duration":5445,"startTime":"2022-12-22T08:21:31.227118400+08:00[Asia/Manila]","screenshots":[{"screenshot":"dbb11210623cb5178d58cd50c352dce1f2097bb674cc20f957abb1bd52684506.png","timeStamp":1671668491238},{"screenshot":"dbb11210623cb5178d58cd50c352dce1f2097bb674cc20f957abb1bd52684506.png","timeStamp":1671668496672}],"result":"SUCCESS","precondition":false,"level":1},{"number":85,"description":"When i click continue button in job information","duration":4256,"startTime":"2022-12-22T08:21:40.869071+08:00[Asia/Manila]","screenshots":[{"screenshot":"ff7794243ef013852353f26e8e11a5f0c84134b0dc5b40e7aca71d29c311c764.png","timeStamp":1671668501084},{"screenshot":"41e8a55bd2c9f123b9912480d6fd72dbd278fcaf18492f5ac7ce8981a5c6057d.png","timeStamp":1671668501908},{"screenshot":"3de9af1a1f329b44f60f407815b6c7db9f2104089a7d60f7e545d121feda18c1.png","timeStamp":1671668505125}],"result":"SUCCESS","precondition":false,"level":1},{"number":86,"description":"When i populate pay group: PeopleNet","duration":25932,"startTime":"2022-12-22T08:22:05.696514+08:00[Asia/Manila]","screenshots":[{"screenshot":"62fb2efc17a5482b0c8a4f390a03795279e737b84735b8079dff53263a9efd83.png","timeStamp":1671668525911},{"screenshot":"f17cdf404d97bde0c9354dd8c1fcd98c4c448cb87e48ad18be09fe9c1ed80232.png","timeStamp":1671668533178},{"screenshot":"170196196f209832da9809a2b9a8506ea230787aa7f034f5cfc141f15ab15ac7.png","timeStamp":1671668551628}],"result":"SUCCESS","precondition":false,"level":1},{"number":87,"description":"When i populate comments in compensation information: COMMENTS_IN_COMPENSATION_INFORMATION","duration":11023,"startTime":"2022-12-22T08:22:31.630969300+08:00[Asia/Manila]","screenshots":[{"screenshot":"170196196f209832da9809a2b9a8506ea230787aa7f034f5cfc141f15ab15ac7.png","timeStamp":1671668551641},{"screenshot":"619268f2c1893308e8009a0306cd0d16ae60a363909c255992f1062a3a1b0c58.png","timeStamp":1671668562654}],"result":"SUCCESS","precondition":false,"level":1},{"number":88,"description":"When i populate next revision date: 01/04/2022","duration":6066,"startTime":"2022-12-22T08:23:33.650354300+08:00[Asia/Manila]","screenshots":[{"screenshot":"62c1fd33353cc7c85ffa6b2da2de637a097dd7f83c32fd7bb3cf41685ed42eb3.png","timeStamp":1671668613895},{"screenshot":"1bd55f4642103de98220d4fe7a2b039aac32cca6c49c20c020de6aaee61d65f1.png","timeStamp":1671668619716}],"result":"SUCCESS","precondition":false,"level":1},{"number":89,"description":"When i click add button in compensation","duration":21607,"startTime":"2022-12-22T08:24:04.315745200+08:00[Asia/Manila]","screenshots":[{"screenshot":"3704a9028ff6c015a23c705ba0b399e78e7bd82fb40e9fab0df463bc31ef198c.png","timeStamp":1671668644552},{"screenshot":"1acd30fa828a2a29dae0137c530f1a386036c82b5af33daa85cfd36a56da6ef9.png","timeStamp":1671668660591},{"screenshot":"1acd30fa828a2a29dae0137c530f1a386036c82b5af33daa85cfd36a56da6ef9.png","timeStamp":1671668665923}],"result":"SUCCESS","precondition":false,"level":1},{"number":90,"description":"When i populate pay component: Base Salary","duration":8816,"startTime":"2022-12-22T08:24:33.897495200+08:00[Asia/Manila]","screenshots":[{"screenshot":"1acd30fa828a2a29dae0137c530f1a386036c82b5af33daa85cfd36a56da6ef9.png","timeStamp":1671668674130},{"screenshot":"6c3354f262b609c2031a520e221e1c79badab6f1e0f8c416ee5fadf5c340fc4e.png","timeStamp":1671668680461},{"screenshot":"4523e4429529a9f965694d6aa84ccdaa3515418d840c7ecb23814bab6c3deef4.png","timeStamp":1671668682713}],"result":"SUCCESS","precondition":false,"level":1},{"number":91,"description":"When i populate amount: 30000","duration":5862,"startTime":"2022-12-22T08:24:42.714648+08:00[Asia/Manila]","screenshots":[{"screenshot":"4523e4429529a9f965694d6aa84ccdaa3515418d840c7ecb23814bab6c3deef4.png","timeStamp":1671668682725},{"screenshot":"364f7668158c9134c96a9479982bfa16e02797e6fc2e4218175379be1ca46f1d.png","timeStamp":1671668688576}],"result":"SUCCESS","precondition":false,"level":1},{"number":92,"description":"Then a reminder pop up message is displayed","duration":25141,"startTime":"2022-12-22T08:24:48.580935300+08:00[Asia/Manila]","screenshots":[{"screenshot":"364f7668158c9134c96a9479982bfa16e02797e6fc2e4218175379be1ca46f1d.png","timeStamp":1671668688592},{"screenshot":"388141b6e2c2c571f6b8e9812100568c52a6f1ecfacabfb79963eebef5db22c4.png","timeStamp":1671668713722}],"result":"SUCCESS","precondition":false,"level":1,"children":[{"number":93,"description":"When i click OK button","duration":24914,"startTime":"2022-12-22T08:24:48.794907100+08:00[Asia/Manila]","screenshots":[{"screenshot":"364f7668158c9134c96a9479982bfa16e02797e6fc2e4218175379be1ca46f1d.png","timeStamp":1671668688984},{"screenshot":"f15fb59fe345e178c7eb4bbe5e80e6b54e7023a57b781d3a6ab0b6d01e558358.png","timeStamp":1671668695060},{"screenshot":"388141b6e2c2c571f6b8e9812100568c52a6f1ecfacabfb79963eebef5db22c4.png","timeStamp":1671668713709}],"result":"SUCCESS","precondition":false,"level":2}]},{"number":94,"description":"When i populate currency: \u003cnull\u003e","duration":21,"startTime":"2022-12-22T08:25:13.724215200+08:00[Asia/Manila]","screenshots":[{"screenshot":"388141b6e2c2c571f6b8e9812100568c52a6f1ecfacabfb79963eebef5db22c4.png","timeStamp":1671668713734},{"screenshot":"388141b6e2c2c571f6b8e9812100568c52a6f1ecfacabfb79963eebef5db22c4.png","timeStamp":1671668713746}],"result":"SUCCESS","precondition":false,"level":1},{"number":95,"description":"When i populate frequency: \u003cnull\u003e","duration":250,"startTime":"2022-12-22T08:25:52.568746300+08:00[Asia/Manila]","screenshots":[{"screenshot":"388141b6e2c2c571f6b8e9812100568c52a6f1ecfacabfb79963eebef5db22c4.png","timeStamp":1671668752809},{"screenshot":"388141b6e2c2c571f6b8e9812100568c52a6f1ecfacabfb79963eebef5db22c4.png","timeStamp":1671668752819}],"result":"SUCCESS","precondition":false,"level":1}]},{"number":96,"description":"When HR admin saves draft: ZCtVSF ZAjAOT","duration":11651,"startTime":"2022-12-22T08:25:52.830847500+08:00[Asia/Manila]","screenshots":[{"screenshot":"b6acbda4516c3d0d7010d9e5c2239d240b20f7d0a9065f6f59687b5e15ec7b49.png","timeStamp":1671668764482}],"result":"SUCCESS","precondition":false,"level":0,"children":[{"number":97,"description":"When i click save draft button","duration":6192,"startTime":"2022-12-22T08:25:52.840432300+08:00[Asia/Manila]","screenshots":[{"screenshot":"068c4c3790b459f90499069b4425972e2b3c9ff799cbcc089103b8f6846640bf.png","timeStamp":1671668753765},{"screenshot":"b6acbda4516c3d0d7010d9e5c2239d240b20f7d0a9065f6f59687b5e15ec7b49.png","timeStamp":1671668759033}],"result":"SUCCESS","precondition":false,"level":1},{"number":98,"description":"Then a confirmation message is displayed after saving draft","duration":5438,"startTime":"2022-12-22T08:25:59.034299500+08:00[Asia/Manila]","screenshots":[{"screenshot":"b6acbda4516c3d0d7010d9e5c2239d240b20f7d0a9065f6f59687b5e15ec7b49.png","timeStamp":1671668759045},{"screenshot":"b6acbda4516c3d0d7010d9e5c2239d240b20f7d0a9065f6f59687b5e15ec7b49.png","timeStamp":1671668764473}],"result":"SUCCESS","precondition":false,"level":1}]},{"number":99,"description":"When HR admin deletes draft: Bea Fe TEJANO, A851754, HRIS2022, Manage Pending Recruits, ZCtVSF ZAjAOT","duration":106301,"startTime":"2022-12-22T08:26:04.483773900+08:00[Asia/Manila]","screenshots":[{"screenshot":"a2fc8f4e2dcabfb0cc9c959c6571921635ec5697a1a864d1fb0bc9fc223f8fe4.png","timeStamp":1671668870785}],"result":"SUCCESS","precondition":false,"level":0,"children":[{"number":100,"description":"Given that I\u0027m logged in to HR space as \u0027Bea Fe TEJANO\u0027","duration":28237,"startTime":"2022-12-22T08:26:04.494767400+08:00[Asia/Manila]","screenshots":[{"screenshot":"9e075c238b4c4cc534961cb46f5cf13a9943d4b60c0c781727ce2b88a42ee190.png","timeStamp":1671668792731}],"result":"SUCCESS","precondition":false,"level":1,"children":[{"number":101,"description":"Given that I\u0027m logged in to HR space using \u0027A851754\u0027 account","duration":12555,"startTime":"2022-12-22T08:26:14.603839400+08:00[Asia/Manila]","screenshots":[{"screenshot":"5286f211277bab15e57c8948ca4656f3f5d76cf0f9081467820a853560a48fc4.png","timeStamp":1671668777537},{"screenshot":"efc2834235131558235f92a5bb93263311c18adc8c8ae01981237dc1b27d3926.png","timeStamp":1671668781580},{"screenshot":"3d68a564e04466f3059cb5bd3809dc7609d1d393cc87e88f7c11adf9605a7e3f.png","timeStamp":1671668787158}],"result":"SUCCESS","precondition":false,"level":2}]},{"number":102,"description":"When i search for an action using the header search bar: Manage Pending Recruits","duration":36427,"startTime":"2022-12-22T08:26:32.733076900+08:00[Asia/Manila]","screenshots":[{"screenshot":"9e075c238b4c4cc534961cb46f5cf13a9943d4b60c0c781727ce2b88a42ee190.png","timeStamp":1671668792744},{"screenshot":"3cea34de274ffc1b56031b2c20a0a82769218c73844662f042880fdcf4862549.png","timeStamp":1671668829161}],"result":"SUCCESS","precondition":false,"level":1},{"number":103,"description":"When i set the filter to drafts: 3","duration":11380,"startTime":"2022-12-22T08:27:09.162001900+08:00[Asia/Manila]","screenshots":[{"screenshot":"3cea34de274ffc1b56031b2c20a0a82769218c73844662f042880fdcf4862549.png","timeStamp":1671668829175},{"screenshot":"abd3eeb0673e2e71fec5f08765d08663d3cfe0c8674b9e32333463300c15fc58.png","timeStamp":1671668834200},{"screenshot":"09394858a3ca8e16b18ee1273fccb9561e465c575e41d5105df9b46e40fe4a55.png","timeStamp":1671668835208},{"screenshot":"221d6c1858cbb3ba7c83350950748828c28f5841e725e6bb992600dbceb9c273.png","timeStamp":1671668840542}],"result":"SUCCESS","precondition":false,"level":1},{"number":104,"description":"When i delete the employee draft: ZCtVSF ZAjAOT","duration":16884,"startTime":"2022-12-22T08:27:20.543882200+08:00[Asia/Manila]","screenshots":[{"screenshot":"221d6c1858cbb3ba7c83350950748828c28f5841e725e6bb992600dbceb9c273.png","timeStamp":1671668840556},{"screenshot":"37a48d0f52863a0715baaae598eb783bcef846d081550d533b6eb57a0e7bace6.png","timeStamp":1671668841251},{"screenshot":"1f5567b106e15534685efa267a7124879bb776e2e97c6c1a5ac8671902dc2742.png","timeStamp":1671668847063},{"screenshot":"a2fc8f4e2dcabfb0cc9c959c6571921635ec5697a1a864d1fb0bc9fc223f8fe4.png","timeStamp":1671668857427}],"result":"SUCCESS","precondition":false,"level":1},{"number":105,"description":"Then the employee name should not be displayed: ZCtVSF ZAjAOT","duration":13346,"startTime":"2022-12-22T08:27:37.428551900+08:00[Asia/Manila]","screenshots":[{"screenshot":"a2fc8f4e2dcabfb0cc9c959c6571921635ec5697a1a864d1fb0bc9fc223f8fe4.png","timeStamp":1671668857443},{"screenshot":"a2fc8f4e2dcabfb0cc9c959c6571921635ec5697a1a864d1fb0bc9fc223f8fe4.png","timeStamp":1671668870775}],"result":"SUCCESS","precondition":false,"level":1}]}],"userStory":{"id":"org.icrc.hrspace.EC.HireAssignTerminate","storyName":"Hire assign terminate","storyClassName":"org.icrc.hrspace.EC.HireAssignTerminate","path":"EC","type":"story"},"featureTag":{"name":"EC/Hire assign terminate","type":"story","displayName":"EC/Hire assign terminate"},"title":"Hire new employee save draft and delete draft","tags":[{"name":"EC/Hire assign terminate","type":"story","displayName":"EC/Hire assign terminate"},{"name":"EC","type":"feature","displayName":"EC"}],"startTime":"2022-12-22T08:03:32.236665500+08:00[Asia/Manila]","duration":1458552,"projectKey":"","sessionId":"18f17d6dafe2b8cd8ae57725ce86a5d7","driver":"chrome","isManualTestingUpToDate":false,"manual":false,"testSource":"JUnit","result":"SUCCESS"}